mutwo/mbrola_converters/__init__.py
mutwo/mbrola_converters/constants.py
mutwo/mbrola_converters/mbrola.py
mutwo.ext_mbrola-0.2.0.dist-info/LICENSE
mutwo.ext_mbrola-0.2.0.dist-info/METADATA
mutwo.ext_mbrola-0.2.0.dist-info/WHEEL
mutwo.ext_mbrola-0.2.0.dist-info/top_level.txt
mutwo.ext_mbrola-0.2.0.dist-info/RECORD
