Metadata-Version: 2.1
Name: mutwo.ext-mbrola
Version: 0.2.0
Summary: mbrola extension for event based framework for generative art
Home-page: https://github.com/mutwo-org/mutwo.ext-mbrola
Author: Levin Eric Zimmermann
Author-email: levin.eric.zimmermann@posteo.eu
License: GPL
Project-URL: Documentation, https://mutwo.readthedocs.io/en/latest/
Platform: UNKNOWN
Requires-Python: >=3.9, <4
License-File: LICENSE
Requires-Dist: mutwo.ext-core (<1.00.0,>=0.55.0)
Requires-Dist: mutwo.ext-music (<1.0.0,>=0.7.0)
Requires-Dist: voxpopuli (<1,>=0.3.7)
Provides-Extra: testing
Requires-Dist: nose ; extra == 'testing'
Requires-Dist: coveralls ; extra == 'testing'
Requires-Dist: sox (==1.4.1) ; extra == 'testing'
Requires-Dist: tensorflow (>=2.0.0) ; extra == 'testing'
Requires-Dist: crepe (==0.0.12) ; extra == 'testing'
